ilstrap/__init__.py
ilstrap/installer.py
ilstrap/shared.py
ilstrap/windows.py
ilstrap/ida_strap/istrapper.py
ilstrap/sys_scripts/get_path.bat
ilstrap-0.3.0.data/scripts/ilstrap
ilstrap-0.3.0.dist-info/METADATA
ilstrap-0.3.0.dist-info/WHEEL
ilstrap-0.3.0.dist-info/top_level.txt
ilstrap-0.3.0.dist-info/RECORD
